wwtiotsdk/__init__.py
wwtiotsdk/influxdb/__init__.py
wwtiotsdk/influxdb/connector.py
wwtiotsdk/influxdb/dataframe_base.py
wwtiotsdk/influxdb/dataframe_records_2d_time.py
wwtiotsdk/influxdb/dataframe_records_3d_time_depth.py
wwtiotsdk/metainfo/__init__.py
wwtiotsdk/metainfo/parameter_lookup.py
wwtiotsdk-0.3.0.dist-info/WHEEL
wwtiotsdk-0.3.0.dist-info/METADATA
wwtiotsdk-0.3.0.dist-info/RECORD
