Metadata-Version: 2.4
Name: wwtiotsdk
Version: 0.3.0
Summary: wwtiotsdk is sdk for ingesting iot data to WWT IoT platform.
Author-email: WaterWebTools Aps <info@waterwebtools.com>
Requires-Dist: influxdb3-python
Requires-Dist: boto3
Project-URL: Home, https://www.waterwebtools.com
